pysimplesql/__init__.py
pysimplesql/pysimplesql.py
pysimplesql-2.3.0.dist-info/LICENSE
pysimplesql-2.3.0.dist-info/METADATA
pysimplesql-2.3.0.dist-info/WHEEL
pysimplesql-2.3.0.dist-info/top_level.txt
pysimplesql-2.3.0.dist-info/RECORD
