Metadata-Version: 2.1
Name: pysimplesql
Version: 2.3.0
Summary: Sqlite3 binding for PySimpleGUI
Home-page: https://github.com/PySimpleSQL/pysimplesql
Author: Jonathan Decker
Author-email: pysimplesql@gmail.com
License: GNU General Public License v3 or later (GPLv3+)
Download-URL: https://github.com/PySimpleSQL/pysimplesql/archive/refs/tags/v2.3.0.tar.gz
Keywords: SQL,sqlite,sqlite3,database,front-end,access,libre office,GUI,PySimpleGUI
Platform: ALL
Classifier: Programming Language :: Python
Classifier: License :: OSI Approved :: GNU General Public License v3 or later (GPLv3+)
Classifier: Topic :: Database :: Front-Ends
Classifier: Operating System :: OS Independent
Requires-Dist: PySimpleGUI
Requires-Dist: update-checker
